nowpayments_api/__init__.py
nowpayments_api/models/__init__.py
nowpayments_api/models/payment.py
nowpayments_api/nowpayments_api.py
nowpayments_api-1.0.2.dist-info/LICENSE
nowpayments_api-1.0.2.dist-info/METADATA
nowpayments_api-1.0.2.dist-info/WHEEL
nowpayments_api-1.0.2.dist-info/RECORD
